goview/__init__.py
goview/admin.py
goview/apps.py
goview/models.py
goview/tests.py
goview/urls.py
goview/views.py
goview/frontend/.DS_Store
goview/frontend/favicon.ico
goview/frontend/index.html
goview/frontend/assets/editor.worker-bdd90286.js
goview/frontend/assets/editor.worker-bdd90286.js.gz
goview/frontend/assets/html.worker-202275bb.js
goview/frontend/assets/html.worker-202275bb.js.gz
goview/frontend/assets/json.worker-139bbbb8.js
goview/frontend/assets/json.worker-139bbbb8.js.gz
goview/frontend/assets/ts.worker-bd2cedec.js
goview/frontend/assets/ts.worker-bd2cedec.js.gz
goview/frontend/monacoeditorwork/editor.worker.bundle.js
goview/frontend/monacoeditorwork/editor.worker.bundle.js.gz
goview/frontend/monacoeditorwork/html.worker.bundle.js
goview/frontend/monacoeditorwork/html.worker.bundle.js.gz
goview/frontend/monacoeditorwork/json.worker.bundle.js
goview/frontend/monacoeditorwork/json.worker.bundle.js.gz
goview/frontend/monacoeditorwork/ts.worker.bundle.js
goview/frontend/monacoeditorwork/ts.worker.bundle.js.gz
goview/frontend/static/.DS_Store
goview/frontend/static/css/403-045f062f.css
goview/frontend/static/css/404-366e2e76.css
goview/frontend/static/css/500-5003991a.css
goview/frontend/static/css/ColorList-98cea65e.css
goview/frontend/static/css/EditorWorker-eb2c5524.css
goview/frontend/static/css/EditorWorker-eb2c5524.css.gz
goview/frontend/static/css/StylesSetting-7ca7a4ce.css
goview/frontend/static/css/StylesSetting-7ca7a4ce.css.gz
goview/frontend/static/css/UnPublish-3bd2924c.css
goview/frontend/static/css/index-0c469725.css
goview/frontend/static/css/index-0c469725.css.gz
goview/frontend/static/css/index-0fb2a60d.css
goview/frontend/static/css/index-0fb2a60d.css.gz
goview/frontend/static/css/index-239d99a1.css
goview/frontend/static/css/index-239d99a1.css.gz
goview/frontend/static/css/index-247c99bc.css
goview/frontend/static/css/index-27c827f9.css
goview/frontend/static/css/index-287b937d.css
goview/frontend/static/css/index-287b937d.css.gz
django_go_view-1.0.2.dist-info/LICENSE
django_go_view-1.0.2.dist-info/METADATA
django_go_view-1.0.2.dist-info/WHEEL
django_go_view-1.0.2.dist-info/top_level.txt
django_go_view-1.0.2.dist-info/RECORD
