Metadata-Version: 2.1
Name: django-go-view
Version: 1.0.2
Summary: An Django extension for Django and GoView
Author-email: Sadam·Sadik <Haoke98@outlook.com>
Maintainer-email: Sadam·Sadik <Haoke98@outlook.com>
License: Apache License
Project-URL: Homepage, https://github.com/Haoke98/django-go-view
Project-URL: Documentation, https://github.com/Haoke98/django-go-view/README.md
Project-URL: Repository, https://github.com/Haoke98/django-go-view.git
Project-URL: Bug Tracker, https://github.com/Haoke98/django-go-view/issues
Project-URL: Changelog, https://github.com/Haoke98/django-go-view/releases
Keywords: django,go-view,goview,django-go-view,screen,bigscreen,echarts,editor
Classifier: Development Status :: 5 - Production/Stable
Classifier: Environment :: Console
Classifier: Intended Audience :: Developers
Classifier: Intended Audience :: Information Technology
Classifier: License :: OSI Approved :: Apache Software License
Classifier: Natural Language :: English
Classifier: Operating System :: OS Independent
Classifier: Programming Language :: Python :: 3.11
Classifier: Programming Language :: Python :: 3.10
Classifier: Programming Language :: Python :: 3.9
Classifier: Programming Language :: Python :: 3.8
Classifier: Programming Language :: Python :: 3.7
Classifier: Programming Language :: Python :: 3.6
Classifier: Topic :: Scientific/Engineering :: Visualization
Classifier: Framework :: Django
Classifier: Framework :: Django CMS
Classifier: 
Requires-Python: >=3.6
License-File: LICENSE
Requires-Dist: django >=4.0.0
